ctesiphon/__init__.py
ctesiphon/modules/__init__.py
ctesiphon/modules/communications/__init__.py
ctesiphon/modules/communications/consumer/__init__.py
ctesiphon/modules/communications/consumer/emails.py
ctesiphon/modules/communications/consumer/router.py
ctesiphon/modules/communications/enums/__init__.py
ctesiphon/modules/communications/enums/email_statuses.py
ctesiphon/modules/communications/enums/email_types.py
ctesiphon/modules/communications/helpers/__init__.py
ctesiphon/modules/communications/helpers/create_email.py
ctesiphon/modules/communications/helpers/send_email.py
ctesiphon/modules/communications/interfaces/__init__.py
ctesiphon/modules/communications/interfaces/container.py
ctesiphon/modules/communications/interfaces/settings.py
ctesiphon/modules/communications/models/__init__.py
ctesiphon/modules/communications/models/email.py
ctesiphon/modules/communications/models/email_settings.py
ctesiphon/modules/communications/settings.py
ctesiphon_communications_service-0.1.0.dist-info/METADATA
ctesiphon_communications_service-0.1.0.dist-info/WHEEL
ctesiphon_communications_service-0.1.0.dist-info/RECORD
