Metadata-Version: 2.1
Name: ctesiphon-communications-service
Version: 0.1.0
Summary: Базовый модуль коммуникаций
License: Apache-2.0
Author: Anton Berdnikov
Author-email: agratoth@yandex.ru
Maintainer: Anton Berdnikov
Maintainer-email: agratoth@yandex.ru
Requires-Python: >=3.11,<3.13
Classifier: License :: OSI Approved :: Apache Software License
Classifier: Programming Language :: Python :: 3
Classifier: Programming Language :: Python :: 3.11
Classifier: Programming Language :: Python :: 3.12
Requires-Dist: ctesiphon (>=0.1.12)
